ms_session/__init__.py
ms_session/api.py
ms_session-1.0.0.dist-info/LICENSE
ms_session-1.0.0.dist-info/METADATA
ms_session-1.0.0.dist-info/WHEEL
ms_session-1.0.0.dist-info/top_level.txt
ms_session-1.0.0.dist-info/RECORD
