Metadata-Version: 2.1
Name: ms-session
Version: 1.0.0
Summary: Library that allows logging into Microsoft accounts via requests
Home-page: https://github.com/zmarffy/ms-session
Author: Zeke Marffy
Author-email: zmarffy@yahoo.com
License: MIT
Platform: UNKNOWN
Requires-Python: >=3.6
Requires-Dist: requests
Requires-Dist: bs4
